raster4ml/__init__.py
raster4ml/extraction.py
raster4ml/features.py
raster4ml/plotting.py
raster4ml/preprocessing.py
raster4ml/utils.py
raster4ml-0.1.4.dist-info/LICENSE
raster4ml-0.1.4.dist-info/METADATA
raster4ml-0.1.4.dist-info/WHEEL
raster4ml-0.1.4.dist-info/top_level.txt
raster4ml-0.1.4.dist-info/RECORD
