Metadata-Version: 2.1
Name: raster4ml
Version: 0.1.4
Summary: A geospatial raster processing library for machine learning
Home-page: https://github.com/remotesensinglab/raster4ml
Author: Sourav Bhadra
Author-email: sbhadra019@gmail.com
Classifier: Programming Language :: Python :: 3
Classifier: License :: OSI Approved :: MIT License
Classifier: Operating System :: OS Independent
Requires-Python: >=3.6
License-File: LICENSE
Requires-Dist: rasterio
Requires-Dist: fiona
Requires-Dist: pyproj
Requires-Dist: rtree
Requires-Dist: shapely
Requires-Dist: geopandas
Requires-Dist: opencv-python
Requires-Dist: notebook
Requires-Dist: tqdm
